[{"title": "Apollo 4 (unmanned mission to test Saturn V)", "images": [{"id": "KSC-67C-7113", "credits": "J.L. Pickering", "description": "Apollo 4 on crawlerway during rollout", "date": "August 26, 1967", "added": "20011031", "links": {"standard": "http://www.hq.nasa.gov/office/pao/History/alsj/a410/ap4-KSC-67C-7113.jpg"}}, {"id": "67-HC-547", "credits": "", "description": "Apollo 4 during rollout", "date": "August 26, 1967", "added": "20020128", "links": {"highres": "http://www.hq.nasa.gov/office/pao/History/alsj/a410/ap4-67-HC-547HR.jpg", "standard": "http://www.hq.nasa.gov/office/pao/History/alsj/a410/ap4-67-HC-547.jpg"}}, {"id": "67-HC-424", "credits": "J.L. Pickering", "description": "Apollo 4 rollout view looking back toward VAB", "date": "August 26, 1967", "added": "20011031", "links": {"standard": "http://www.hq.nasa.gov/office/pao/History/alsj/a410/ap4-67-HC-424.jpg"}}, {"id": "KSC-67PC-381", "credits": "J.L. Pickering", "description": "Apollo 4 rollout - passing Mobile Service Structure", "date": "August 26, 1967", "added": "20020324", "links": {"standard": "http://www.hq.nasa.gov/office/pao/History/alsj/a410/ap4-KSC-67PC-381.jpg"}}, {"id": "S67-43595", "credits": "J.L. Pickering", "description": "Apollo 4 passing palm trees during rollout", "date": "August 26, 1967", "added": "20011031", "links": {"standard": "http://www.hq.nasa.gov/office/pao/History/alsj/a410/ap4-S67-43595.jpg"}}, {"id": "KSC-67PC-367", "credits": "J.L. Pickering", "description": "Apollo 4 rollout", "date": "August 26, 1967", "added": "20031101", "links": {"standard": "http://www.hq.nasa.gov/office/pao/History/alsj/a410/ap4-KSC-67PC-367.jpg"}}, {"id": "S67-43593", "credits": "", "description": "SA-501 at pad 39A - Note the mid-S-IC stage paintover", "date": "August 26, 1967", "added": "20010601", "links": {"highres": "http://www.hq.nasa.gov/office/pao/History/alsj/a410/ap4-S67-43593HR.jpg", "standard": "http://www.hq.nasa.gov/office/pao/History/alsj/a410/ap4-S67-43593.jpg"}}, {"id": "AP4-MSS-NOID", "credits": "J.L. Pickering", "description": "Apollo 4 after rollout with MSS being moved into position", "date": "August 26, 1967", "added": "20030322", "links": {"standard": "http://www.hq.nasa.gov/office/pao/History/alsj/a410/ap4-mss-noID.jpg"}}, {"id": "67-HC-552", "credits": "", "description": "Closeup aerial view of Apollo 4 on pad 39A during a Countdown Demonstration Test", "date": "October 10, 1967", "added": "20001118", "links": {"highres": "http://www.hq.nasa.gov/office/pao/History/alsj/a410/ap4-67-HC-552HR.jpg", "standard": "http://www.hq.nasa.gov/office/pao/History/alsj/a410/ap4-67-HC-552.jpg"}}, {"id": "AP4-NIGHT-B2-NOID", "credits": "J.L. Pickering", "description": "night view of Apollo 4 on pad", "date": "\u00a0", "added": "20030322", "links": {"standard": "http://www.hq.nasa.gov/office/pao/History/alsj/a410/ap4-night-b2-noID.jpg"}}, {"id": "AP4-NIGHT-B1-NOID", "credits": "J.L. Pickering", "description": "Apollo 4 Saturn V on pad at night", "date": "\u00a0", "added": "20030323", "links": {"standard": "http://www.hq.nasa.gov/office/pao/History/alsj/a410/ap4-night-b1-noID.jpg"}}, {"id": "S67-50531", "credits": "", "description": "Early morning view of Pad A, Launch Complex 39, Kennedy Space Center, showing Apollo 4 (Spacecraft 017/Saturn 501) prior to launch", "date": "November 9, 1967", "added": "19990104", "links": {"highres": "http://www.hq.nasa.gov/office/pao/History/alsj/a410/ap4-S67-50531HR.jpg", "standard": "http://www.hq.nasa.gov/office/pao/History/alsj/a410/ap4-S67-50531.jpg"}}, {"id": "KSC-67PC-435", "credits": "", "description": "The first Saturn V lifts off from pad 39-A", "date": "November 9, 1967", "added": "19990416", "links": {"highres": "http://www.hq.nasa.gov/office/pao/History/alsj/a410/ap4-KSC-67PC-435HR.jpg", "standard": "http://www.hq.nasa.gov/office/pao/History/alsj/a410/ap4-KSC-67PC-435.jpg"}}, {"id": "KSC-67PC-437", "credits": "J.L. Pickering", "description": "launch of Apollo 4", "date": "November 9, 1967", "added": "20020623", "links": {"standard": "http://www.hq.nasa.gov/office/pao/History/alsj/a410/ap4-KSC-67PC-437.jpg"}}, {"id": "AP4-LIFTOFF-A-NOID", "credits": "J.L. Pickering", "description": "liftoff of Apollo 4", "date": "\u00a0", "added": "20030323", "links": {"standard": "http://www.hq.nasa.gov/office/pao/History/alsj/a410/ap4-liftoff-a-noID.jpg"}}, {"id": "AP4-LIFTOFF-B-NOID", "credits": "J.L. Pickering", "description": "liftoff of Apollo 4", "date": "\u00a0", "added": "20030323", "links": {"standard": "http://www.hq.nasa.gov/office/pao/History/alsj/a410/ap4-liftoff-b-noID.jpg"}}, {"id": "KSC-67P-601", "credits": "J.L. Pickering", "description": "Apollo 4 liftoff", "date": "\u00a0", "added": "20030322", "links": {"standard": "http://www.hq.nasa.gov/office/pao/History/alsj/a410/ap4-KSC-67P-601.jpg"}}, {"id": "KSC-88PC-1407", "credits": "", "description": "Apollo 4 rides a column of fire in the first unmanned Saturn V test", "date": "November 9, 1967", "added": "19990206", "links": {"standard": "http://www.hq.nasa.gov/office/pao/History/alsj/a410/ap4-KSC-88PC-1407.jpg"}}, {"id": "67-HC-745", "credits": "", "description": "Apollo 4 climbs toward orbit", "date": "November 9, 1967", "added": "20020423", "links": {"highres": "http://www.hq.nasa.gov/office/pao/History/alsj/a410/ap4-67-HC-745HR.jpg", "standard": "http://www.hq.nasa.gov/office/pao/History/alsj/a410/ap4-67-HC-745.jpg"}}, {"id": "AS4-1-410", "credits": "", "description": "view of the Earth from an automatic camera on Apollo 4", "date": "November 9, 1967", "added": "19990311", "links": {"highres": "http://www.hq.nasa.gov/office/pao/History/alsj/a410/AS4-1-410HR.jpg", "standard": "http://www.hq.nasa.gov/office/pao/History/alsj/a410/AS4-1-410.jpg"}}]}]