[{"title": "", "images": [{"id": "AS15-84-11275", "credits": "JSC scan", "description": "STA 2 / S wall / Hadley Rille", "date": "\u00a0", "added": "20060409", "links": {"highres": "https://www.hq.nasa.gov/office/pao/History/alsj/a15/AS15-84-11275HR.jpg", "standard": "https://www.hq.nasa.gov/office/pao/History/alsj/a15/AS15-84-11275.jpg"}}, {"id": "AS15-84-11276", "credits": "JSC scan", "description": "STA 2 / S wall / Hadley Rille", "date": "\u00a0", "added": "20060409", "links": {"highres": "https://www.hq.nasa.gov/office/pao/History/alsj/a15/AS15-84-11276HR.jpg", "standard": "https://www.hq.nasa.gov/office/pao/History/alsj/a15/AS15-84-11276.jpg"}}, {"id": "AS15-84-11277", "credits": "JSC scan", "description": "STA 2 / S wall / Hadley Rille", "date": "\u00a0", "added": "20060409", "links": {"highres": "https://www.hq.nasa.gov/office/pao/History/alsj/a15/AS15-84-11277HR.jpg", "standard": "https://www.hq.nasa.gov/office/pao/History/alsj/a15/AS15-84-11277.jpg"}}, {"id": "AS15-84-11278", "credits": "JSC scan", "description": "STA 2 / S wall / Hadley Rille", "date": "\u00a0", "added": "20060409", "links": {"highres": "https://www.hq.nasa.gov/office/pao/History/alsj/a15/AS15-84-11278HR.jpg", "standard": "https://www.hq.nasa.gov/office/pao/History/alsj/a15/AS15-84-11278.jpg"}}, {"id": "AS15-84-11279", "credits": "JSC scan", "description": "STA 2 / S wall / Hadley Rille", "date": "\u00a0", "added": "20060409", "links": {"highres": "https://www.hq.nasa.gov/office/pao/History/alsj/a15/AS15-84-11279HR.jpg", "standard": "https://www.hq.nasa.gov/office/pao/History/alsj/a15/AS15-84-11279.jpg"}}, {"id": "AS15-84-11280", "credits": "JSC scan", "description": "STA 2 / S wall / Hadley Rille", "date": "\u00a0", "added": "20060409", "links": {"highres": "https://www.hq.nasa.gov/office/pao/History/alsj/a15/AS15-84-11280HR.jpg", "standard": "https://www.hq.nasa.gov/office/pao/History/alsj/a15/AS15-84-11280.jpg"}}, {"id": "AS15-84-11281", "credits": "JSC scan", "description": "STA 2 / S wall / Hadley Rille", "date": "\u00a0", "added": "20060409", "links": {"highres": "https://www.hq.nasa.gov/office/pao/History/alsj/a15/AS15-84-11281HR.jpg", "standard": "https://www.hq.nasa.gov/office/pao/History/alsj/a15/AS15-84-11281.jpg"}}, {"id": "AS15-84-11282", "credits": "JSC scan", "description": "STA 2 / S wall / Hadley Rille", "date": "\u00a0", "added": "20060409", "links": {"highres": "https://www.hq.nasa.gov/office/pao/History/alsj/a15/AS15-84-11282HR.jpg", "standard": "https://www.hq.nasa.gov/office/pao/History/alsj/a15/AS15-84-11282.jpg"}}, {"id": "AS15-84-11283", "credits": "JSC scan", "description": "STA 2 / S wall / Hadley Rille", "date": "\u00a0", "added": "20060409", "links": {"highres": "https://www.hq.nasa.gov/office/pao/History/alsj/a15/AS15-84-11283HR.jpg", "standard": "https://www.hq.nasa.gov/office/pao/History/alsj/a15/AS15-84-11283.jpg"}}, {"id": "AS15-84-11284", "credits": "JSC scan", "description": "Station 2 / Hadley Rille (500mm)", "date": "\u00a0", "added": "20060409", "links": {"highres": "https://www.hq.nasa.gov/office/pao/History/alsj/a15/AS15-84-11284HR.jpg", "standard": "https://www.hq.nasa.gov/office/pao/History/alsj/a15/AS15-84-11284.jpg"}}, {"id": "AS15-84-11285", "credits": "JSC scan", "description": "Station 2 / Hadley Rille (500mm)", "date": "\u00a0", "added": "20060409", "links": {"highres": "https://www.hq.nasa.gov/office/pao/History/alsj/a15/AS15-84-11285HR.jpg", "standard": "https://www.hq.nasa.gov/office/pao/History/alsj/a15/AS15-84-11285.jpg"}}, {"id": "AS15-84-11286", "credits": "JSC scan", "description": "Station 2 / Hadley Rille (500mm)", "date": "\u00a0", "added": "20060409", "links": {"highres": "https://www.hq.nasa.gov/office/pao/History/alsj/a15/AS15-84-11286HR.jpg", "standard": "https://www.hq.nasa.gov/office/pao/History/alsj/a15/AS15-84-11286.jpg"}}, {"id": "AS15-84-11287", "credits": "JSC scan", "description": "Station 2 / Hadley Rille (500mm)", "date": "\u00a0", "added": "20060409", "links": {"highres": "https://www.hq.nasa.gov/office/pao/History/alsj/a15/AS15-84-11287HR.jpg", "standard": "https://www.hq.nasa.gov/office/pao/History/alsj/a15/AS15-84-11287.jpg"}}, {"id": "AS15-84-11288", "credits": "JSC scan", "description": "Station 2 / Hadley Rille (500mm)", "date": "\u00a0", "added": "20060409", "links": {"highres": "https://www.hq.nasa.gov/office/pao/History/alsj/a15/AS15-84-11288HR.jpg", "standard": "https://www.hq.nasa.gov/office/pao/History/alsj/a15/AS15-84-11288.jpg"}}, {"id": "AS15-84-11289", "credits": "JSC scan", "description": "(description not yet available)", "date": "\u00a0", "added": "20060409", "links": {"highres": "https://www.hq.nasa.gov/office/pao/History/alsj/a15/AS15-84-11289HR.jpg", "standard": "https://www.hq.nasa.gov/office/pao/History/alsj/a15/AS15-84-11289.jpg"}}, {"id": "AS15-84-11290", "credits": "JSC scan", "description": "(description not yet available)", "date": "\u00a0", "added": "20060409", "links": {"highres": "https://www.hq.nasa.gov/office/pao/History/alsj/a15/AS15-84-11290HR.jpg", "standard": "https://www.hq.nasa.gov/office/pao/History/alsj/a15/AS15-84-11290.jpg"}}, {"id": "AS15-84-11291", "credits": "JSC scan", "description": "(description not yet available)", "date": "\u00a0", "added": "20060409", "links": {"highres": "https://www.hq.nasa.gov/office/pao/History/alsj/a15/AS15-84-11291HR.jpg", "standard": "https://www.hq.nasa.gov/office/pao/History/alsj/a15/AS15-84-11291.jpg"}}, {"id": "AS15-84-11292", "credits": "JSC scan", "description": "Mt. Hadley viewed from Station 6 (500mm)", "date": "\u00a0", "added": "20060409", "links": {"highres": "https://www.hq.nasa.gov/office/pao/History/alsj/a15/AS15-84-11292HR.jpg", "standard": "https://www.hq.nasa.gov/office/pao/History/alsj/a15/AS15-84-11292.jpg"}}, {"id": "AS15-84-11293", "credits": "JSC scan", "description": "(description not yet available)", "date": "\u00a0", "added": "20060409", "links": {"highres": "https://www.hq.nasa.gov/office/pao/History/alsj/a15/AS15-84-11293HR.jpg", "standard": "https://www.hq.nasa.gov/office/pao/History/alsj/a15/AS15-84-11293.jpg"}}, {"id": "AS15-84-11294", "credits": "JSC scan", "description": "(description not yet available)", "date": "\u00a0", "added": "20060409", "links": {"highres": "https://www.hq.nasa.gov/office/pao/History/alsj/a15/AS15-84-11294HR.jpg", "standard": "https://www.hq.nasa.gov/office/pao/History/alsj/a15/AS15-84-11294.jpg"}}]}]