[{"title": "", "images": [{"id": "AS17-146-22349", "credits": "JSC scan", "description": "(description not yet available)", "date": "\u00a0", "added": "20060715", "links": {"highres": "https://www.hq.nasa.gov/office/pao/History/alsj/a17/AS17-146-22349HR.jpg", "standard": "https://www.hq.nasa.gov/office/pao/History/alsj/a17/AS17-146-22349.jpg"}}, {"id": "AS17-146-22350", "credits": "JSC scan", "description": "(description not yet available)", "date": "\u00a0", "added": "20060715", "links": {"highres": "https://www.hq.nasa.gov/office/pao/History/alsj/a17/AS17-146-22350HR.jpg", "standard": "https://www.hq.nasa.gov/office/pao/History/alsj/a17/AS17-146-22350.jpg"}}, {"id": "AS17-146-22351", "credits": "JSC scan", "description": "(description not yet available)", "date": "\u00a0", "added": "20060715", "links": {"highres": "https://www.hq.nasa.gov/office/pao/History/alsj/a17/AS17-146-22351HR.jpg", "standard": "https://www.hq.nasa.gov/office/pao/History/alsj/a17/AS17-146-22351.jpg"}}, {"id": "AS17-146-22352", "credits": "JSC scan", "description": "(description not yet available)", "date": "\u00a0", "added": "20060715", "links": {"highres": "https://www.hq.nasa.gov/office/pao/History/alsj/a17/AS17-146-22352HR.jpg", "standard": "https://www.hq.nasa.gov/office/pao/History/alsj/a17/AS17-146-22352.jpg"}}, {"id": "AS17-146-22353", "credits": "JSC scan", "description": "(description not yet available)", "date": "\u00a0", "added": "20060715", "links": {"highres": "https://www.hq.nasa.gov/office/pao/History/alsj/a17/AS17-146-22353HR.jpg", "standard": "https://www.hq.nasa.gov/office/pao/History/alsj/a17/AS17-146-22353.jpg"}}, {"id": "AS17-146-22354", "credits": "JSC scan", "description": "(description not yet available)", "date": "\u00a0", "added": "20060715", "links": {"highres": "https://www.hq.nasa.gov/office/pao/History/alsj/a17/AS17-146-22354HR.jpg", "standard": "https://www.hq.nasa.gov/office/pao/History/alsj/a17/AS17-146-22354.jpg"}}, {"id": "AS17-146-22355", "credits": "JSC scan", "description": "Station 7 pan frame", "date": "\u00a0", "added": "20060715", "links": {"highres": "https://www.hq.nasa.gov/office/pao/History/alsj/a17/AS17-146-22355HR.jpg", "standard": "https://www.hq.nasa.gov/office/pao/History/alsj/a17/AS17-146-22355.jpg"}}, {"id": "AS17-146-22356", "credits": "JSC scan", "description": "(description not yet available)", "date": "\u00a0", "added": "20060715", "links": {"highres": "https://www.hq.nasa.gov/office/pao/History/alsj/a17/AS17-146-22356HR.jpg", "standard": "https://www.hq.nasa.gov/office/pao/History/alsj/a17/AS17-146-22356.jpg"}}, {"id": "AS17-146-22357", "credits": "JSC scan", "description": "(description not yet available)", "date": "\u00a0", "added": "20060715", "links": {"highres": "https://www.hq.nasa.gov/office/pao/History/alsj/a17/AS17-146-22357HR.jpg", "standard": "https://www.hq.nasa.gov/office/pao/History/alsj/a17/AS17-146-22357.jpg"}}, {"id": "AS17-146-22358", "credits": "JSC scan", "description": "(description not yet available)", "date": "\u00a0", "added": "20060715", "links": {"highres": "https://www.hq.nasa.gov/office/pao/History/alsj/a17/AS17-146-22358HR.jpg", "standard": "https://www.hq.nasa.gov/office/pao/History/alsj/a17/AS17-146-22358.jpg"}}, {"id": "AS17-146-22359", "credits": "JSC scan", "description": "(description not yet available)", "date": "\u00a0", "added": "20060715", "links": {"highres": "https://www.hq.nasa.gov/office/pao/History/alsj/a17/AS17-146-22359HR.jpg", "standard": "https://www.hq.nasa.gov/office/pao/History/alsj/a17/AS17-146-22359.jpg"}}, {"id": "AS17-146-22360", "credits": "JSC scan", "description": "(description not yet available)", "date": "\u00a0", "added": "20060715", "links": {"highres": "https://www.hq.nasa.gov/office/pao/History/alsj/a17/AS17-146-22360HR.jpg", "standard": "https://www.hq.nasa.gov/office/pao/History/alsj/a17/AS17-146-22360.jpg"}}, {"id": "AS17-146-22361", "credits": "JSC scan", "description": "(description not yet available)", "date": "\u00a0", "added": "20060715", "links": {"highres": "https://www.hq.nasa.gov/office/pao/History/alsj/a17/AS17-146-22361HR.jpg", "standard": "https://www.hq.nasa.gov/office/pao/History/alsj/a17/AS17-146-22361.jpg"}}, {"id": "AS17-146-22362", "credits": "JSC scan", "description": "(description not yet available)", "date": "\u00a0", "added": "20060715", "links": {"highres": "https://www.hq.nasa.gov/office/pao/History/alsj/a17/AS17-146-22362HR.jpg", "standard": "https://www.hq.nasa.gov/office/pao/History/alsj/a17/AS17-146-22362.jpg"}}, {"id": "AS17-146-22363", "credits": "JSC scan", "description": "(description not yet available)", "date": "\u00a0", "added": "20060715", "links": {"highres": "https://www.hq.nasa.gov/office/pao/History/alsj/a17/AS17-146-22363HR.jpg", "standard": "https://www.hq.nasa.gov/office/pao/History/alsj/a17/AS17-146-22363.jpg"}}, {"id": "AS17-146-22364", "credits": "JSC scan", "description": "Station 7 pan frame", "date": "\u00a0", "added": "20060715", "links": {"highres": "https://www.hq.nasa.gov/office/pao/History/alsj/a17/AS17-146-22364HR.jpg", "standard": "https://www.hq.nasa.gov/office/pao/History/alsj/a17/AS17-146-22364.jpg"}}, {"id": "AS17-146-22365", "credits": "JSC scan", "description": "Station 8 / left image of stereo pair of sample 8135", "date": "\u00a0", "added": "20060715", "links": {"highres": "https://www.hq.nasa.gov/office/pao/History/alsj/a17/AS17-146-22365HR.jpg", "standard": "https://www.hq.nasa.gov/office/pao/History/alsj/a17/AS17-146-22365.jpg"}}, {"id": "AS17-146-22366", "credits": "JSC scan", "description": "Station 8 / right image of stereo pair of sample 8135", "date": "\u00a0", "added": "20060715", "links": {"highres": "https://www.hq.nasa.gov/office/pao/History/alsj/a17/AS17-146-22366HR.jpg", "standard": "https://www.hq.nasa.gov/office/pao/History/alsj/a17/AS17-146-22366.jpg"}}, {"id": "AS17-146-22367", "credits": "JSC scan", "description": "The Lunar Rover parked at Station 8", "date": "\u00a0", "added": "20060715", "links": {"highres": "https://www.hq.nasa.gov/office/pao/History/alsj/a17/AS17-146-22367HR.jpg", "standard": "https://www.hq.nasa.gov/office/pao/History/alsj/a17/AS17-146-22367.jpg"}}, {"id": "AS17-146-22368", "credits": "JSC scan", "description": "Station 8 samples", "date": "\u00a0", "added": "20060715", "links": {"highres": "https://www.hq.nasa.gov/office/pao/History/alsj/a17/AS17-146-22368HR.jpg", "standard": "https://www.hq.nasa.gov/office/pao/History/alsj/a17/AS17-146-22368.jpg"}}]}]