[{"title": "", "images": [{"id": "AS16-107-17459", "credits": "JSC scan", "description": "(description not yet available)", "date": "\u00a0", "added": "20060122", "links": {"highres": "https://www.hq.nasa.gov/office/pao/History/alsj/a16/AS16-107-17459HR.jpg", "standard": "https://www.hq.nasa.gov/office/pao/History/alsj/a16/AS16-107-17459.jpg"}}, {"id": "AS16-107-17460", "credits": "JSC scan", "description": "(description not yet available)", "date": "\u00a0", "added": "20060122", "links": {"highres": "https://www.hq.nasa.gov/office/pao/History/alsj/a16/AS16-107-17460HR.jpg", "standard": "https://www.hq.nasa.gov/office/pao/History/alsj/a16/AS16-107-17460.jpg"}}, {"id": "AS16-107-17461", "credits": "JSC scan", "description": "Sta 4 / sample 399 soil", "date": "\u00a0", "added": "20060122", "links": {"highres": "https://www.hq.nasa.gov/office/pao/History/alsj/a16/AS16-107-17461HR.jpg", "standard": "https://www.hq.nasa.gov/office/pao/History/alsj/a16/AS16-107-17461.jpg"}}, {"id": "AS16-107-17462", "credits": "JSC scan", "description": "Sta 4 / sample 399 soil", "date": "\u00a0", "added": "20060122", "links": {"highres": "https://www.hq.nasa.gov/office/pao/History/alsj/a16/AS16-107-17462HR.jpg", "standard": "https://www.hq.nasa.gov/office/pao/History/alsj/a16/AS16-107-17462.jpg"}}, {"id": "AS16-107-17463", "credits": "JSC scan", "description": "Sta 4 / sample 400 soil", "date": "\u00a0", "added": "20060122", "links": {"highres": "https://www.hq.nasa.gov/office/pao/History/alsj/a16/AS16-107-17463HR.jpg", "standard": "https://www.hq.nasa.gov/office/pao/History/alsj/a16/AS16-107-17463.jpg"}}, {"id": "AS16-107-17464", "credits": "JSC scan", "description": "Sta 4 / sample 400 soil", "date": "\u00a0", "added": "20060122", "links": {"highres": "https://www.hq.nasa.gov/office/pao/History/alsj/a16/AS16-107-17464HR.jpg", "standard": "https://www.hq.nasa.gov/office/pao/History/alsj/a16/AS16-107-17464.jpg"}}, {"id": "AS16-107-17465", "credits": "JSC scan", "description": "Sta 4 / samples 400 soil / 401 rock", "date": "\u00a0", "added": "20060122", "links": {"highres": "https://www.hq.nasa.gov/office/pao/History/alsj/a16/AS16-107-17465HR.jpg", "standard": "https://www.hq.nasa.gov/office/pao/History/alsj/a16/AS16-107-17465.jpg"}}, {"id": "AS16-107-17466", "credits": "JSC scan", "description": "Sta 4 / samples 400 soil / 401 rock", "date": "\u00a0", "added": "20060122", "links": {"highres": "https://www.hq.nasa.gov/office/pao/History/alsj/a16/AS16-107-17466HR.jpg", "standard": "https://www.hq.nasa.gov/office/pao/History/alsj/a16/AS16-107-17466.jpg"}}, {"id": "AS16-107-17467", "credits": "JSC scan", "description": "(description not yet available)", "date": "\u00a0", "added": "20060122", "links": {"highres": "https://www.hq.nasa.gov/office/pao/History/alsj/a16/AS16-107-17467HR.jpg", "standard": "https://www.hq.nasa.gov/office/pao/History/alsj/a16/AS16-107-17467.jpg"}}, {"id": "AS16-107-17468", "credits": "JSC scan", "description": "Sta 4 pan frame", "date": "\u00a0", "added": "20060122", "links": {"highres": "https://www.hq.nasa.gov/office/pao/History/alsj/a16/AS16-107-17468HR.jpg", "standard": "https://www.hq.nasa.gov/office/pao/History/alsj/a16/AS16-107-17468.jpg"}}, {"id": "AS16-107-17469", "credits": "JSC scan", "description": "Sta 4 pan", "date": "\u00a0", "added": "20060122", "links": {"highres": "https://www.hq.nasa.gov/office/pao/History/alsj/a16/AS16-107-17469HR.jpg", "standard": "https://www.hq.nasa.gov/office/pao/History/alsj/a16/AS16-107-17469.jpg"}}, {"id": "AS16-107-17470", "credits": "JSC scan", "description": "Sta 4 pan", "date": "\u00a0", "added": "20060122", "links": {"highres": "https://www.hq.nasa.gov/office/pao/History/alsj/a16/AS16-107-17470HR.jpg", "standard": "https://www.hq.nasa.gov/office/pao/History/alsj/a16/AS16-107-17470.jpg"}}, {"id": "AS16-107-17471", "credits": "JSC scan", "description": "Sta 4 pan", "date": "\u00a0", "added": "20060122", "links": {"highres": "https://www.hq.nasa.gov/office/pao/History/alsj/a16/AS16-107-17471HR.jpg", "standard": "https://www.hq.nasa.gov/office/pao/History/alsj/a16/AS16-107-17471.jpg"}}, {"id": "AS16-107-17472", "credits": "JSC scan", "description": "Sta 4 pan", "date": "\u00a0", "added": "20060122", "links": {"highres": "https://www.hq.nasa.gov/office/pao/History/alsj/a16/AS16-107-17472HR.jpg", "standard": "https://www.hq.nasa.gov/office/pao/History/alsj/a16/AS16-107-17472.jpg"}}, {"id": "AS16-107-17473", "credits": "JSC scan", "description": "Sta 4 pan", "date": "\u00a0", "added": "20060122", "links": {"highres": "https://www.hq.nasa.gov/office/pao/History/alsj/a16/AS16-107-17473HR.jpg", "standard": "https://www.hq.nasa.gov/office/pao/History/alsj/a16/AS16-107-17473.jpg"}}, {"id": "AS16-107-17474", "credits": "JSC scan", "description": "Sta 4 pan", "date": "\u00a0", "added": "20060122", "links": {"highres": "https://www.hq.nasa.gov/office/pao/History/alsj/a16/AS16-107-17474HR.jpg", "standard": "https://www.hq.nasa.gov/office/pao/History/alsj/a16/AS16-107-17474.jpg"}}, {"id": "AS16-107-17475", "credits": "JSC scan", "description": "Sta 4 pan", "date": "\u00a0", "added": "20060122", "links": {"highres": "https://www.hq.nasa.gov/office/pao/History/alsj/a16/AS16-107-17475HR.jpg", "standard": "https://www.hq.nasa.gov/office/pao/History/alsj/a16/AS16-107-17475.jpg"}}, {"id": "AS16-107-17476", "credits": "JSC scan", "description": "Sta 4 pan", "date": "\u00a0", "added": "20060122", "links": {"highres": "https://www.hq.nasa.gov/office/pao/History/alsj/a16/AS16-107-17476HR.jpg", "standard": "https://www.hq.nasa.gov/office/pao/History/alsj/a16/AS16-107-17476.jpg"}}, {"id": "AS16-107-17477", "credits": "JSC scan", "description": "Sta 4 pan", "date": "\u00a0", "added": "20060122", "links": {"highres": "https://www.hq.nasa.gov/office/pao/History/alsj/a16/AS16-107-17477HR.jpg", "standard": "https://www.hq.nasa.gov/office/pao/History/alsj/a16/AS16-107-17477.jpg"}}, {"id": "AS16-107-17478", "credits": "JSC scan", "description": "Sta 4 pan", "date": "\u00a0", "added": "20060122", "links": {"highres": "https://www.hq.nasa.gov/office/pao/History/alsj/a16/AS16-107-17478HR.jpg", "standard": "https://www.hq.nasa.gov/office/pao/History/alsj/a16/AS16-107-17478.jpg"}}]}]