[{"title": "Apollo 17 Pre-Flight Photos", "images": [{"id": "72-HC-873", "credits": "research: J.L. Pickering", "description": "Apollo 17 crew at base of Saturn V during visit to pad", "date": "December 4, 1972", "added": "20050213", "links": {"highres": "http://www.hq.nasa.gov/office/pao/History/alsj/a17/ap17-72-HC-873HR.jpg", "standard": "http://www.hq.nasa.gov/office/pao/History/alsj/a17/ap17-72-HC-873.jpg"}}, {"id": "KSC-72P-536", "credits": "J.L. Pickering", "description": "(description not yet available)", "date": "\u00a0", "added": "20030323", "links": {"standard": "http://www.hq.nasa.gov/office/pao/History/alsj/a17/ap17-KSC-72P-536.jpg"}}, {"id": "KSC-72P-537", "credits": "J.L. Pickering", "description": "(description not yet available)", "date": "December 4, 1972", "added": "20030323", "links": {"standard": "http://www.hq.nasa.gov/office/pao/History/alsj/a17/ap17-KSC-72P-537.jpg"}}, {"id": "KSC-72C-5706BW", "credits": "J.L. Pickering", "description": "Apollo 17 LM-12 ALSEP closeout photo", "date": "December 5, 1972", "added": "20030323", "links": {"standard": "http://www.hq.nasa.gov/office/pao/History/alsj/a17/ap17-KSC-72C-5706BW.jpg"}}, {"id": "KSC-72PC-612", "credits": "", "description": "The Apollo 17 crew at the traditional pre-launch breakfast", "date": "December 6, 1972", "added": "20010211", "links": {"highres": "http://www.hq.nasa.gov/office/pao/History/alsj/a17/ap17-KSC-72PC-612HR.jpg", "standard": "http://www.hq.nasa.gov/office/pao/History/alsj/a17/ap17-KSC-72PC-612.jpg"}}, {"id": "72-HC-877", "credits": "research: J.L. Pickering", "description": "Apollo 17 crew during pre-flight dinner in crew quarters", "date": "December 6, 1972", "added": "20050213", "links": {"highres": "http://www.hq.nasa.gov/office/pao/History/alsj/a17/ap17-72-HC-877HR.jpg", "standard": "http://www.hq.nasa.gov/office/pao/History/alsj/a17/ap17-72-HC-877.jpg"}}, {"id": "KSC-72P-547", "credits": "NASA", "description": "Alan Shepard jokes with Jack Schmitt during suitup", "date": "December 6, 1972", "added": "20001013", "links": {"standard": "http://www.hq.nasa.gov/office/pao/History/alsj/a17/ap17-KSC-72P-547.jpg"}}, {"id": "72-HC-878", "credits": "research: J.L. Pickering", "description": "Gene Cernan undergoes final spacesuit pressure checks", "date": "December 6, 1972", "added": "20050213", "links": {"highres": "http://www.hq.nasa.gov/office/pao/History/alsj/a17/ap17-72-HC-878HR.jpg", "standard": "http://www.hq.nasa.gov/office/pao/History/alsj/a17/ap17-72-HC-878.jpg"}}, {"id": "72-HC-879", "credits": "research: J.L. Pickering", "description": "Ron Evans relaxes during pre-launch spacesuit pressure checks", "date": "December 6, 1972", "added": "20050213", "links": {"highres": "http://www.hq.nasa.gov/office/pao/History/alsj/a17/ap17-72-HC-879HR.jpg", "standard": "http://www.hq.nasa.gov/office/pao/History/alsj/a17/ap17-72-HC-879.jpg"}}, {"id": "72-HC-880", "credits": "research: J.L. Pickering", "description": "Jack Schmitt undergoes final spacesuit pressure checks", "date": "December 6, 1972", "added": "20050213", "links": {"highres": "http://www.hq.nasa.gov/office/pao/History/alsj/a17/ap17-72-HC-880HR.jpg", "standard": "http://www.hq.nasa.gov/office/pao/History/alsj/a17/ap17-72-HC-880.jpg"}}, {"id": "KSC-72P-544", "credits": "J.L. Pickering", "description": "(description not yet available)", "date": "December 6, 1972", "added": "20030323", "links": {"standard": "http://www.hq.nasa.gov/office/pao/History/alsj/a17/ap17-KSC-72P-544.jpg"}}, {"id": "KSC-72P-546", "credits": "J.L. Pickering", "description": "Apollo 17 CMP Ronald Evans shakes hands with Donald K. \"Deke\" Slayton, Director of Flight Crew Operations at the Manned Spacecraft Center", "date": "December 6, 1972", "added": "20030323", "links": {"standard": "http://www.hq.nasa.gov/office/pao/History/alsj/a17/ap17-KSC-72P-546.jpg"}}, {"id": "KSC-72P-539", "credits": "J.L. Pickering", "description": "(description not yet available)", "date": "December 6, 1972", "added": "20030323", "links": {"standard": "http://www.hq.nasa.gov/office/pao/History/alsj/a17/ap17-KSC-72P-539.jpg"}}, {"id": "72-HC-884", "credits": "research: J.L. Pickering", "description": "Alabama Governor George Wallace waves to well wishers at the Kennedy Space Center during Apollo 17 prelaunch activities.", "date": "December 7, 1972", "added": "20050213", "links": {"standard": "http://www.hq.nasa.gov/office/pao/History/alsj/a17/ap17-72-HC-884.jpg"}}, {"id": "KSC-72P-545", "credits": "J.L. Pickering", "description": "Technicians check Apollo 17 Mission Commander Eugene Cernan's spacesuit during preflight preparations", "date": "December 6, 1972", "added": "20030323", "links": {"standard": "http://www.hq.nasa.gov/office/pao/History/alsj/a17/ap17-KSC-72P-545.jpg"}}, {"id": "S72-54881", "credits": "", "description": "Gene Kranz briefing Neil Hutchinson and Gerald Griffin at Mission Contol during Apollo 17 launch delay", "date": "December 6, 1972", "added": "20020701", "links": {"highres": "http://www.hq.nasa.gov/office/pao/History/alsj/a17/ap17-S72-54881HR.jpg", "standard": "http://www.hq.nasa.gov/office/pao/History/alsj/a17/ap17-S72-54881.jpg"}}, {"id": "72-H-1516", "credits": "J.L. Pickering", "description": "Cernan waves to well-wishers as he and other Apollo 17 crewmembers leave the suiting area for brief ride to launch pad", "date": "December 6, 1972", "added": "20030323", "links": {"standard": "http://www.hq.nasa.gov/office/pao/History/alsj/a17/ap17-72-H-1516.jpg"}}, {"id": "72-H-1517", "credits": "J.L. Pickering", "description": "Gene Cernan says goodbye to his family during the Apollo 17 walkout.  KSC Security Chief Charlie Buckey is on the right", "date": "December 6, 1972", "added": "20011031", "links": {"standard": "http://www.hq.nasa.gov/office/pao/History/alsj/a17/ap17-72-H-1517.jpg"}}, {"id": "KSC-72PC-616", "credits": "", "description": "Ron Evans says goodbye to his wife as he and his crewmates leave the MSOB on their way to pad 39-A", "date": "December 6, 1972", "added": "20030817", "links": {"highres": "http://www.hq.nasa.gov/office/pao/History/alsj/a17/ap17-KSC-72PC-616HR.jpg", "standard": "http://www.hq.nasa.gov/office/pao/History/alsj/a17/ap17-KSC-72PC-616.jpg"}}, {"id": "72-HC-881", "credits": "research: J.L. Pickering", "description": "Ron Evans says goodbye to his wife as the Apollo 17 crew leaves the Manned Spacecraft Operations Bldg en route to the launch pad", "date": "December 6, 1972", "added": "20050213", "links": {"highres": "http://www.hq.nasa.gov/office/pao/History/alsj/a17/ap17-72-HC-881HR.jpg", "standard": "http://www.hq.nasa.gov/office/pao/History/alsj/a17/ap17-72-HC-881.jpg"}}]}]